ttsfrd/__init__.py
ttsfrd-0.1.0.dist-info/METADATA
ttsfrd-0.1.0.dist-info/WHEEL
ttsfrd-0.1.0.dist-info/top_level.txt
ttsfrd-0.1.0.dist-info/RECORD
